boggled/__init__.py
boggled/boggle_board.py
boggled/boggle_dice.py
boggled/boggle_solver.py
boggled/boggle_words.py
boggled-1.0.0.dist-info/LICENSE
boggled-1.0.0.dist-info/METADATA
boggled-1.0.0.dist-info/WHEEL
boggled-1.0.0.dist-info/top_level.txt
boggled-1.0.0.dist-info/RECORD
