Metadata-Version: 2.1
Name: boggled
Version: 1.0.0
Summary: Simple Boggle game solver and generator.
Home-page: https://github.com/danag/boggled
Author: Dan Nagle
Author-email: d.a.nagle@gmail.com
License: UNKNOWN
Platform: UNKNOWN
Classifier: Programming Language :: Python :: 3
Classifier: License :: OSI Approved :: MIT License
Classifier: Operating System :: OS Independent
